setup.py
bochi_distribution/Binomialdistribution.py
bochi_distribution/Gaussiandistribution.py
bochi_distribution/Generaldistribution.py
bochi_distribution/__init__.py
bochi_distribution.egg-info/PKG-INFO
bochi_distribution.egg-info/SOURCES.txt
bochi_distribution.egg-info/dependency_links.txt
bochi_distribution.egg-info/not-zip-safe
bochi_distribution.egg-info/top_level.txt