Metadata-Version: 1.0
Name: bochi-distribution
Version: 1.0
Summary: Gaussian and Binomial distributions
Home-page: UNKNOWN
Author: Tanya Singh-Mishra
Author-email: UNKNOWN
License: UNKNOWN
Platform: UNKNOWN
